RKPairip/RKPairip.py
RKPairip/__init__.py
RKPairip-4.0.dist-info/LICENSE
RKPairip-4.0.dist-info/METADATA
RKPairip-4.0.dist-info/WHEEL
RKPairip-4.0.dist-info/entry_points.txt
RKPairip-4.0.dist-info/top_level.txt
RKPairip-4.0.dist-info/RECORD
