Metadata-Version: 2.1
Name: RKPairip
Version: 4.0
Summary: Remove Pairip Protection with RKPairip Script & Recover String & Rebuild Apk
Home-page: https://github.com/Technoindian/RKPairip
Author: RK_TECHNO_INDIA
Author-email: TechnoIndia786@gmail.com
Classifier: Programming Language :: Python :: 3
Classifier: License :: OSI Approved :: MIT License
Classifier: Operating System :: OS Independent
Requires-Python: >=3.12
License-File: LICENSE
